flipkart_scrapping/FlipkartScrapping.py
flipkart_scrapping/__init__.py
flipkart_scrapping/config/__init__.py
flipkart_scrapping/config/logger.py
flipkart_scrapping/extract_details/__init__.py
flipkart_scrapping/extract_details/page.py
flipkart_scrapping/extract_details/product.py
flipkart_scrapping/extract_details/ratings.py
flipkart_scrapping/extract_details/reviews.py
flipkart_scrapping/file_oper/__init__.py
flipkart_scrapping/file_oper/create_file.py
flipkart_scrapping/file_oper/write_to_file.py
flipkart_scrapping/modules/__init__.py
flipkart_scrapping/modules/content.py
flipkart_scrapping/modules/html_page_parser.py
flipkart_scrapping/modules/update_comments.py
flipkart_scrapping/mongo_operations/__init__.py
flipkart_scrapping/mongo_operations/connectToMongo.py
flipkart_scrapping/mongo_operations/insertIntoMongo.py
flipkart_scrapping/mongo_operations/mongoOper.py
flipkart_scrapping/settings/__init__.py
flipkart_scrapping/settings/settings.py
flipkart_scrapping-0.0.16.dist-info/METADATA
flipkart_scrapping-0.0.16.dist-info/WHEEL
flipkart_scrapping-0.0.16.dist-info/top_level.txt
flipkart_scrapping-0.0.16.dist-info/RECORD
